yafowil.widget.ace-1.3-py3.9-nspkg.pth
yafowil/widget/ace/__init__.py
yafowil/widget/ace/example.py
yafowil/widget/ace/tests.py
yafowil/widget/ace/widget.py
yafowil/widget/ace/resources/widget.css
yafowil/widget/ace/resources/widget.js
yafowil/widget/ace/resources/ace/ace.js
yafowil/widget/ace/resources/ace/keybinding-emacs.js
yafowil/widget/ace/resources/ace/keybinding-vim.js
yafowil/widget/ace/resources/ace/mode-c9search.js
yafowil/widget/ace/resources/ace/mode-c_cpp.js
yafowil/widget/ace/resources/ace/mode-clojure.js
yafowil/widget/ace/resources/ace/mode-coffee.js
yafowil/widget/ace/resources/ace/mode-coldfusion.js
yafowil/widget/ace/resources/ace/mode-csharp.js
yafowil/widget/ace/resources/ace/mode-css.js
yafowil/widget/ace/resources/ace/mode-diff.js
yafowil/widget/ace/resources/ace/mode-glsl.js
yafowil/widget/ace/resources/ace/mode-golang.js
yafowil/widget/ace/resources/ace/mode-groovy.js
yafowil/widget/ace/resources/ace/mode-haxe.js
yafowil/widget/ace/resources/ace/mode-html.js
yafowil/widget/ace/resources/ace/mode-jade.js
yafowil/widget/ace/resources/ace/mode-java.js
yafowil/widget/ace/resources/ace/mode-javascript.js
yafowil/widget/ace/resources/ace/mode-json.js
yafowil/widget/ace/resources/ace/mode-jsp.js
yafowil/widget/ace/resources/ace/mode-jsx.js
yafowil/widget/ace/resources/ace/mode-latex.js
yafowil/widget/ace/resources/ace/mode-less.js
yafowil/widget/ace/resources/ace/mode-liquid.js
yafowil/widget/ace/resources/ace/mode-lua.js
yafowil/widget/ace/resources/ace/mode-luahtml.js
yafowil/widget/ace/resources/ace/mode-luapage.js
yafowil/widget/ace/resources/ace/mode-markdown.js
yafowil/widget/ace/resources/ace/mode-ocaml.js
yafowil/widget/ace/resources/ace/mode-perl.js
yafowil/widget/ace/resources/ace/mode-pgsql.js
yafowil/widget/ace/resources/ace/mode-php.js
yafowil/widget/ace/resources/ace/mode-powershell.js
yafowil/widget/ace/resources/ace/mode-python.js
yafowil/widget/ace/resources/ace/mode-ruby.js
yafowil/widget/ace/resources/ace/mode-scad.js
yafowil_widget_ace-1.3.dist-info/licenses/LICENSE.rst
yafowil_widget_ace-1.3.dist-info/METADATA
yafowil_widget_ace-1.3.dist-info/WHEEL
yafowil_widget_ace-1.3.dist-info/entry_points.txt
yafowil_widget_ace-1.3.dist-info/namespace_packages.txt
yafowil_widget_ace-1.3.dist-info/top_level.txt
yafowil_widget_ace-1.3.dist-info/RECORD
